{
  "prestashop": [
    {
      "prestashop_min": "1.7.0.0",
      "prestashop_max": "8.2.3",
      "recommended": true,
      "autoupgrade_recommended": {
        "last_version": "7.3.0",
        "download": {
          "link": "https://github.com/PrestaShop/autoupgrade/releases/download/v7.3.0/autoupgrade-v7.3.0.zip",
          "md5": "48ced9086bac4f2e2266c3d20505e58c"
        }
      }
    },
    {
      "prestashop_min": "9.0.0",
      "prestashop_max": "9.0.1",
      "recommended": false,
      "autoupgrade_recommended": {
        "last_version": "7.4.1",
        "download": {
          "link": "https://github.com/PrestaShop/autoupgrade/releases/download/v7.4.1/autoupgrade-v7.4.1.zip",
          "md5": "28a29a7e50bb3bbedc79789b5df5656a"
        }
      }
    },
    {
      "prestashop_min": "1.6.0.0",
      "prestashop_max": "1.7.8.11",
      "recommended": true,
      "autoupgrade_recommended": {
        "last_version": "4.14.4",
        "download": {
          "link": "https://github.com/PrestaShop/autoupgrade/releases/download/v4.14.4/autoupgrade-v4.14.4.zip",
          "md5": "76cc875318c82bb2fb3b1650d574f822"
        }
      }
    }
  ]
}
